odoo/addons/account_invoice_refund_line_selection/README.rst
odoo/addons/account_invoice_refund_line_selection/__init__.py
odoo/addons/account_invoice_refund_line_selection/__manifest__.py
odoo/addons/account_invoice_refund_line_selection/i18n/account_invoice_refund_line_selection.pot
odoo/addons/account_invoice_refund_line_selection/i18n/de.po
odoo/addons/account_invoice_refund_line_selection/i18n/es.po
odoo/addons/account_invoice_refund_line_selection/models/__init__.py
odoo/addons/account_invoice_refund_line_selection/models/account_invoice.py
odoo/addons/account_invoice_refund_line_selection/static/description/icon.png
odoo/addons/account_invoice_refund_line_selection/tests/__init__.py
odoo/addons/account_invoice_refund_line_selection/tests/test_refund_line.py
odoo/addons/account_invoice_refund_line_selection/wizards/__init__.py
odoo/addons/account_invoice_refund_line_selection/wizards/account_invoice_refund.py
odoo/addons/account_invoice_refund_line_selection/wizards/account_invoice_refund_view.xml
odoo11_addon_account_invoice_refund_line_selection-11.0.1.0.0.99.dev7.dist-info/METADATA
odoo11_addon_account_invoice_refund_line_selection-11.0.1.0.0.99.dev7.dist-info/WHEEL
odoo11_addon_account_invoice_refund_line_selection-11.0.1.0.0.99.dev7.dist-info/top_level.txt
odoo11_addon_account_invoice_refund_line_selection-11.0.1.0.0.99.dev7.dist-info/RECORD
